librogect/__init__.py
librogect/main.py
librogect-1.1.4.dist-info/METADATA
librogect-1.1.4.dist-info/WHEEL
librogect-1.1.4.dist-info/top_level.txt
librogect-1.1.4.dist-info/RECORD
